pypkgs_yh/__init__.py
pypkgs_yh/pypkgs_yh.py
pypkgs_yh-0.1.0.dist-info/LICENSE
pypkgs_yh-0.1.0.dist-info/WHEEL
pypkgs_yh-0.1.0.dist-info/METADATA
pypkgs_yh-0.1.0.dist-info/RECORD
